infi_logger/__init__.py
infi_logger/elastic_logger.py
infi_logger/elastic_search_sender.py
infi_logger/elasticsearch_connection.py
infi_logger/local_logs_writer.py
infi_logger/consts/__init__.py
infi_logger/consts/consts.py
tests/__init__.py
tests/conftest.py
tests/test_elastic_logger.py
tests/test_elastic_search_sender.py
tests/test_elasticsearch_connection.py
tests/test_local_logs_writer.py
infi_logger-0.55.dist-info/METADATA
infi_logger-0.55.dist-info/WHEEL
infi_logger-0.55.dist-info/top_level.txt
infi_logger-0.55.dist-info/RECORD
