Metadata-Version: 2.1
Name: infi-logger
Version: 0.55
Summary: Logger package for infinity team
Author: Infinity Team
License: MIT
Requires-Dist: certifi ==2023.7.22 ; python_version >= "3.6"
Requires-Dist: elastic-transport ==8.10.0 ; python_version >= "3.6"
Requires-Dist: elasticsearch ==8.10.1 ; python_version >= "3.6" and python_version < "4"
Requires-Dist: iniconfig ==2.0.0 ; python_version >= "3.7"
Requires-Dist: packaging ==23.2 ; python_version >= "3.7"
Requires-Dist: pytest ==7.4.3 ; python_version >= "3.7"
Requires-Dist: urllib3 ==2.0.7 ; python_version >= "3.7"
Requires-Dist: pluggy ==1.3.0 ; python_version >= "3.8"
Requires-Dist: python-dotenv ==1.0.0 ; python_version >= "3.8"
Requires-Dist: colorama ==0.4.6 ; sys_platform == "win32"
